scrapy_mingle
