Metadata-Version: 1.1
Name: Scrapy-mingle
Version: 0.1.29
Summary: Some useful tools for Scrapy
Home-page: https://github.com/xuhaomin/scrapy_mingle
Author: xuhaomin
Author-email: xhmgreat@sina.com
License: BSD
Platform: UNKNOWN
Classifier: Development Status :: 3 - Alpha
Classifier: Intended Audience :: Developers
Classifier: License :: OSI Approved :: BSD License
Classifier: Operating System :: OS Independent
Classifier: Programming Language :: Python
Classifier: Framework :: Scrapy
Classifier: Programming Language :: Python :: 3
Classifier: Programming Language :: Python :: 3.3
Classifier: Programming Language :: Python :: 3.4
Classifier: Programming Language :: Python :: 3.5
Classifier: Programming Language :: Python :: 3.6
